maxcolor.py
maxcolor-1.0.2.dist-info/WHEEL
maxcolor-1.0.2.dist-info/METADATA
maxcolor-1.0.2.dist-info/RECORD
