Metadata-Version: 2.1
Name: maxcolor
Version: 1.0.2
Summary: A module to genereate gradient text and rich panels.
License: MIT
Author-email: maxludden <dev@maxludden.com>
Requires-Python: >=3.10
Requires-Dist: maxconsole>=0.5.1
Requires-Dist: rich>=12.6.0
